langchain_nvidia_aiplay/__init__.py
langchain_nvidia_aiplay-0.0.2.dist-info/METADATA
langchain_nvidia_aiplay-0.0.2.dist-info/WHEEL
langchain_nvidia_aiplay-0.0.2.dist-info/RECORD
