Metadata-Version: 2.1
Name: langchain-nvidia-aiplay
Version: 0.0.2
Summary: This package is deprecated. Please use langchain-nvidia-ai-endpoints instead.
Home-page: https://github.com/langchain-ai/langchain/tree/master/libs/partners/nvidia-ai-endpoints
Requires-Python: >=3.8.1,<4.0
Classifier: Programming Language :: Python :: 3
Classifier: Programming Language :: Python :: 3.9
Classifier: Programming Language :: Python :: 3.10
Classifier: Programming Language :: Python :: 3.11
Requires-Dist: langchain-nvidia-ai-endpoints
Project-URL: Repository, https://github.com/langchain-ai/langchain/tree/master/libs/partners/nvidia-ai-endpoints
